fastavro/__init__.py
fastavro/__main__.py
fastavro/_logical_readers.cpython-314t-aarch64-linux-gnu.so
fastavro/_logical_readers.pyi
fastavro/_logical_readers_py.py
fastavro/_logical_readers_py.pyi
fastavro/_logical_writers.cpython-314t-aarch64-linux-gnu.so
fastavro/_logical_writers.pyi
fastavro/_logical_writers_py.py
fastavro/_logical_writers_py.pyi
fastavro/_read.cpython-314t-aarch64-linux-gnu.so
fastavro/_read.pyi
fastavro/_read_common.py
fastavro/_read_py.py
fastavro/_schema.cpython-314t-aarch64-linux-gnu.so
fastavro/_schema.pyi
fastavro/_schema_common.py
fastavro/_schema_py.py
fastavro/_validate_common.py
fastavro/_validation.cpython-314t-aarch64-linux-gnu.so
fastavro/_validation.pyi
fastavro/_validation_py.py
fastavro/_write.cpython-314t-aarch64-linux-gnu.so
fastavro/_write.pyi
fastavro/_write_common.py
fastavro/_write_py.py
fastavro/const.py
fastavro/json_read.py
fastavro/json_write.py
fastavro/logical_readers.py
fastavro/logical_writers.py
fastavro/py.typed
fastavro/read.py
fastavro/schema.py
fastavro/types.py
fastavro/utils.py
fastavro/validation.py
fastavro/write.py
fastavro/io/__init__.py
fastavro/io/binary_decoder.py
fastavro/io/binary_encoder.py
fastavro/io/json_decoder.py
fastavro/io/json_encoder.py
fastavro/io/parser.py
fastavro/io/symbols.py
fastavro/repository/__init__.py
fastavro/repository/base.py
fastavro/repository/flat_dict.py
fastavro-1.12.1.dist-info/METADATA
fastavro-1.12.1.dist-info/WHEEL
fastavro-1.12.1.dist-info/entry_points.txt
fastavro-1.12.1.dist-info/top_level.txt
fastavro-1.12.1.dist-info/RECORD
fastavro-1.12.1.dist-info/licenses/LICENSE
fastavro-1.12.1.dist-info/licenses/NOTICE.txt
