Metadata-Version: 2.1
Name: fastavro
Version: 1.12.1
Summary: Fast read/write of AVRO files
Home-page: https://github.com/fastavro/fastavro
Author: Miki Tebeka
Author-email: miki.tebeka@gmail.com
License: MIT
Classifier: Development Status :: 5 - Production/Stable
Classifier: Intended Audience :: Developers
Classifier: Operating System :: POSIX :: Linux
Classifier: Operating System :: Microsoft :: Windows
Classifier: Operating System :: MacOS
Classifier: Programming Language :: Python :: 3
Classifier: Programming Language :: Python :: 3.9
Classifier: Programming Language :: Python :: 3.10
Classifier: Programming Language :: Python :: 3.11
Classifier: Programming Language :: Python :: 3.12
Classifier: Programming Language :: Python :: 3.13
Classifier: Programming Language :: Python :: 3.14
Classifier: Programming Language :: Python :: Implementation :: CPython
Classifier: Programming Language :: Python :: Implementation :: PyPy
Classifier: Programming Language :: Python
Classifier: Topic :: Software Development :: Libraries :: Python Modules
Classifier: Topic :: Software Development :: Libraries
Classifier: Topic :: Scientific/Engineering :: Information Analysis
Requires-Python: >=3.9
License-File: LICENSE
License-File: NOTICE.txt
Provides-Extra: codecs
Requires-Dist: cramjam; extra == "codecs"
Requires-Dist: zstandard; extra == "codecs"
Requires-Dist: lz4; extra == "codecs"
Provides-Extra: lz4
Requires-Dist: lz4; extra == "lz4"
Provides-Extra: snappy
Requires-Dist: cramjam; extra == "snappy"
Provides-Extra: zstandard
Requires-Dist: zstandard; extra == "zstandard"
